pantomath/__init__.py
pantomath-1.0.dist-info/METADATA
pantomath-1.0.dist-info/WHEEL
pantomath-1.0.dist-info/top_level.txt
pantomath-1.0.dist-info/zip-safe
pantomath-1.0.dist-info/RECORD
