Metadata-Version: 2.1
Name: pantomath
Version: 1.0
Summary: I want to know everything
Home-page: UNKNOWN
Author: Idin
Author-email: py@idin.ca
License: GNU AGPLv3
Platform: UNKNOWN
Classifier: Development Status :: 3 - Alpha
Classifier: Intended Audience :: Developers
Classifier: Programming Language :: Python :: 3 :: Only
Classifier: Programming Language :: Python :: 3.6
Classifier: Programming Language :: Python :: 3.7
Classifier: Topic :: Software Development :: Libraries :: Python Modules
Requires-Python: ~=3.6
